aardwolfgui/__init__.py
aardwolfgui/_version.py
aardwolfgui/aardpclient.py
aardwolfgui/aardpclient_simple.py
aardwolfgui-0.0.8.dist-info/LICENSE
aardwolfgui-0.0.8.dist-info/METADATA
aardwolfgui-0.0.8.dist-info/WHEEL
aardwolfgui-0.0.8.dist-info/entry_points.txt
aardwolfgui-0.0.8.dist-info/top_level.txt
aardwolfgui-0.0.8.dist-info/RECORD
