Metadata-Version: 2.1
Name: aardwolfgui
Version: 0.0.8
Summary: GUI for aardwolf RD/VNC client
Home-page: https://github.com/skelsec/aardwolfgui
Author: Tamas Jos
Author-email: info@skelsecprojects.com
Classifier: Programming Language :: Python :: 3.8
Classifier: Operating System :: OS Independent
Requires-Python: >=3.7
License-File: LICENSE
Requires-Dist: aardwolf (>=0.2.7)
Requires-Dist: pyperclip
Requires-Dist: Pillow
Requires-Dist: pyqt6
